pythora/__init__.py
pythora/app.py
pythora/middleware.py
pythora/response.py
pythora-0.1.3.dist-info/METADATA
pythora-0.1.3.dist-info/WHEEL
pythora-0.1.3.dist-info/top_level.txt
pythora-0.1.3.dist-info/RECORD
