Metadata-Version: 2.1
Name: pythora
Version: 0.1.3
Summary: Python Web Framework built for learning purposes
Home-page: https://github.com/johnibek/pythora
Author: Jonibek Hamroqulov
Author-email: jonibekhamroqulov2004@gmail.com
License: MIT
Classifier: License :: OSI Approved :: MIT License
Classifier: Programming Language :: Python
Classifier: Programming Language :: Python :: 3
Classifier: Programming Language :: Python :: 3.6
Classifier: Programming Language :: Python :: Implementation :: CPython
Classifier: Programming Language :: Python :: Implementation :: PyPy
Requires-Python: >=3.12.0
Requires-Dist: requests==2.32.3
Requires-Dist: parse==1.20.2
Requires-Dist: webob==1.8.7
Requires-Dist: gunicorn==23.0.0
Requires-Dist: requests-wsgi-adapter==0.4.1
Requires-Dist: Jinja2==3.1.4
Requires-Dist: whitenoise==6.7.0
